salt_cumulus/__init__.py
salt_cumulus/loader.py
salt_cumulus/states/__init__.py
salt_cumulus/states/cumulus.py
salt_cumulus-0.0.3.dist-info/LICENSE
salt_cumulus-0.0.3.dist-info/METADATA
salt_cumulus-0.0.3.dist-info/WHEEL
salt_cumulus-0.0.3.dist-info/entry_points.txt
salt_cumulus-0.0.3.dist-info/top_level.txt
salt_cumulus-0.0.3.dist-info/RECORD
