Metadata-Version: 2.1
Name: salt-cumulus
Version: 0.0.3
Summary: Small salt module providing cumulus.managed, to apply basic config on cumulus switches
Home-page: https://github.com/ArcaniteSolutions/salt-cumulus
Author: Maximilien Cuony
Author-email: maximilien.cuony@arcanite.ch
License: MPL
Platform: UNKNOWN
Classifier: Development Status :: 4 - Beta
Classifier: Intended Audience :: System Administrators
Classifier: License :: OSI Approved :: Mozilla Public License 2.0 (MPL 2.0)
Classifier: Operating System :: Other OS
Classifier: Programming Language :: Python
Classifier: Topic :: System :: Networking
Requires-Dist: sh
